garpyclient/__init__.py
garpyclient/client.py
garpyclient/resources/default_config.yaml
garpyclient/settings.py
garpyclient-0.1.1.dist-info/LICENSE
garpyclient-0.1.1.dist-info/WHEEL
garpyclient-0.1.1.dist-info/METADATA
garpyclient-0.1.1.dist-info/RECORD
