Metadata-Version: 2.1
Name: garpyclient
Version: 0.1.1
Summary: Basic library for authenticating and querying Garmin Connect
Home-page: https://github.com/felipeam86/garpyclient
License: MIT
Author: Felipe Aguirre Martinez
Author-email: felipeam86@gmail.com
Requires-Python: >=3.7.9,<4.0.0
Classifier: License :: OSI Approved :: MIT License
Classifier: Programming Language :: Python :: 3
Classifier: Programming Language :: Python :: 3.10
Classifier: Programming Language :: Python :: 3.8
Classifier: Programming Language :: Python :: 3.9
Provides-Extra: cloudscraper
Requires-Dist: PyYAML (>=5.1,<7.0)
Requires-Dist: cloudscraper (>=1.2.58,<2.0.0); extra == "cloudscraper"
Requires-Dist: requests (>=2.22,<3.0)
